eurec4a_synop/__init__.py
eurec4a_synop/plot.py
eurec4a_synop/images/20200101000000.png
eurec4a_synop/images/20200102000000.png
eurec4a_synop/images/20200103000000.png
eurec4a_synop/images/20200107000000.png
eurec4a_synop/images/20200108000000.png
eurec4a_synop/images/20200109000000.png
eurec4a_synop/images/20200110000000.png
eurec4a_synop/images/20200111000000.png
eurec4a_synop/images/20200112000000.png
eurec4a_synop/images/20200113000000.png
eurec4a_synop/images/20200114000000.png
eurec4a_synop/images/20200115000000.png
eurec4a_synop/images/20200116000000.png
eurec4a_synop/images/20200117000000.png
eurec4a_synop/images/20200118000000.png
eurec4a_synop/images/20200119000000.png
eurec4a_synop/images/20200120000000.png
eurec4a_synop/images/20200121000000.png
eurec4a_synop/images/20200122000000.png
eurec4a_synop/images/20200123000000.png
eurec4a_synop/images/20200125000000.png
eurec4a_synop/images/20200126000000.png
eurec4a_synop/images/20200127000000.png
eurec4a_synop/images/20200128000000.png
eurec4a_synop/images/20200129000000.png
eurec4a_synop/images/20200130000000.png
eurec4a_synop/images/20200131000000.png
eurec4a_synop/images/20200201000000.png
eurec4a_synop/images/20200202000000.png
eurec4a_synop/images/20200203000000.png
eurec4a_synop/images/20200204000000.png
eurec4a_synop/images/20200206000000.png
eurec4a_synop/images/20200207000000.png
eurec4a_synop/images/20200208000000.png
eurec4a_synop/images/20200209000000.png
eurec4a_synop/images/20200210000000.png
eurec4a_synop/images/20200211000000.png
eurec4a_synop/images/20200212000000.png
eurec4a_synop/images/20200213000000.png
eurec4a_synop/images/20200214000000.png
eurec4a_synop/images/20200215000000.png
eurec4a_synop/images/20200216000000.png
eurec4a_synop/images/20200217000000.png
eurec4a_synop/images/20200219000000.png
eurec4a_synop/images/20200221000000.png
eurec4a_synop/images/20200222000000.png
eurec4a_synop/images/20200223000000.png
eurec4a_synop/images/20200224000000.png
eurec4a_synop-0.1.0.dist-info/METADATA
eurec4a_synop-0.1.0.dist-info/WHEEL
eurec4a_synop-0.1.0.dist-info/top_level.txt
eurec4a_synop-0.1.0.dist-info/RECORD
