Metadata-Version: 2.1
Name: eurec4a-synop
Version: 0.1.0
Summary: Synoptic chart plots for EUREC4A
Home-page: https://github.com/leifdenby/eurec4a_synop
Author: Leif Denby
Author-email: leif@denby.eu
License: UNKNOWN
Platform: UNKNOWN
Requires-Dist: cartopy
Provides-Extra: dev
Requires-Dist: pytest ; extra == 'dev'
Requires-Dist: flake8 ; extra == 'dev'
Provides-Extra: lint
Requires-Dist: flake8 ; extra == 'lint'
Provides-Extra: test
Requires-Dist: pytest ; extra == 'test'
